R0State/R0State.py
R0State/__init__.py
R0State/data/Means_BOL_ICD1_ICD2.csv
R0State-0.591.dist-info/METADATA
R0State-0.591.dist-info/WHEEL
R0State-0.591.dist-info/top_level.txt
R0State-0.591.dist-info/RECORD
