Metadata-Version: 2.1
Name: R0State
Version: 0.591
Summary: Returning interpolated R0_BOL
Home-page: https://github.com/___empty/___empty
Author: Lukas Merkle
Author-email: lukas.merkle@tum.de
License: UNKNOWN
Platform: UNKNOWN
Classifier: Programming Language :: Python :: 3
Classifier: License :: OSI Approved :: MIT License
Classifier: Operating System :: OS Independent
Requires-Dist: numpy
Requires-Dist: pandas
